{
  "task_id": "7d1fddff-ee58-4244-90e6-ffe05fd126d5",
  "plan_id": "e4fba3ea-866e-4fb4-a342-b1ca10919d5a",
  "status": "failed",
  "started_at": "2026-02-20T02:00:02Z",
  "ended_at": "2026-02-20T02:00:02Z",
  "agent": "file",
  "events": [
    {
      "timestamp": "2026-02-20T02:00:02Z",
      "level": "info",
      "step_id": null,
      "message": "Approval token validated",
      "details": {
        "token_id": "fab830ef-393f-4078-bea2-5e443fb8696b"
      }
    },
    {
      "timestamp": "2026-02-20T02:00:02Z",
      "level": "info",
      "step_id": "s1",
      "message": "Executing file.read_text",
      "details": {
        "preview": "Read text from file"
      }
    }
  ],
  "error": "HTTP exception during execution"
}