{
  "task_id": "a2a32ac6-4dce-4cdb-91cb-863e5ff1d3ca",
  "plan_id": "681e95b4-d123-4b9c-b8a4-52b9c0cd91f1",
  "status": "completed",
  "started_at": "2026-02-20T01:56:41Z",
  "ended_at": "2026-02-20T01:56:41Z",
  "agent": "shell",
  "events": [
    {
      "timestamp": "2026-02-20T01:56:41Z",
      "level": "info",
      "step_id": null,
      "message": "Approval token validated",
      "details": {
        "token_id": "4194c6a6-29b5-4ba4-ad5e-4a0da2ac0e92"
      }
    },
    {
      "timestamp": "2026-02-20T01:56:41Z",
      "level": "info",
      "step_id": "s1",
      "message": "Executing shell.exec",
      "details": {
        "preview": "Run grep TODO sample.txt"
      }
    },
    {
      "timestamp": "2026-02-20T01:56:41Z",
      "level": "info",
      "step_id": "s1",
      "message": "shell command preview",
      "details": {
        "argv": [
          "grep",
          "TODO",
          "sample.txt"
        ],
        "cwd": "C:\\Users\\17868\\AppData\\Local\\Temp\\pytest-of-17868\\pytest-12\\test_internal_commands_work0"
      }
    },
    {
      "timestamp": "2026-02-20T01:56:41Z",
      "level": "info",
      "step_id": "s1",
      "message": "shell command completed",
      "details": {
        "exit_code": 0,
        "timed_out": false,
        "truncated": false,
        "output": "C:\\Users\\17868\\AppData\\Local\\Temp\\pytest-of-17868\\pytest-12\\test_internal_commands_work0\\sample.txt:2:TODO line\n"
      }
    }
  ],
  "error": null
}